<?xml version="1.0" encoding="UTF-8"?>
<!--
	Copyright (c) 2018, Vernalis (R&D) Ltd
	This program is free software; you can redistribute it and/or modify it
	under the terms of the GNU General Public License, Version 3, as
	published by the Free Software Foundation.

	This program is distributed in the hope that it will be useful, but
	WITHOUT ANY WARRANTY; without even the implied warranty of
	MERCHANTABILITY or FITNESS FOR A PARTICULAR PURPOSE.
	See the GNU General Public License for more details.

	You should have received a copy of the GNU General Public License
	along with this program; if not, see <http://www.gnu.org/licenses>
-->
<knimeNode
	icon="3D_Dist.png"
	type="Manipulator"
	xmlns="http://knime.org/node/v3.1"
	xmlns:xsi="http://www.w3.org/2001/XMLSchema-instance"
	xsi:schemaLocation="http://knime.org/node/v3.1 http://knime.org/node/v3.1.xsd">
	<name>Vector Distance (3-D)</name>

	<shortDescription>
		This node calculates the vector distance between two points
		in 3-D space
	</shortDescription>

	<fullDescription>
		<intro>
			<p>This node calculates the vector distance between two points in 3-D
				Euclidean space (i.e [x1-x0, y1-y0, z1-z0]). The coordinates are contained in 6 numerical
				columns.
			</p>
			<p>
				This node was developed by
				<a href="http://www.vernalis-research.com/">Vernalis Research (Cambridge, UK)</a>
				.
				For feedback and more information, please contact
				<a href="mailto:knime@vernalis.com">knime@vernalis.com</a>
			</p>
		</intro>


		<option name="x0">The x-coordinate of the first point
		</option>
		<option name="y0">The y-coordinate of the first point
		</option>
		<option name="z0">The z-coordinate of the first point
		</option>

		<option name="x1">The x-coordinate of the second point
		</option>
		<option name="y1">The y-coordinate of the second point
		</option>
		<option name="z1">The z-coordinate of the second point
		</option>

			</fullDescription>

	<ports>
		<inPort
			index="0"
			name="3-D Points">Port containing 3-D points</inPort>
		<outPort
			index="0"
			name="Distances">Port with 3-D distances added</outPort>
	</ports>

</knimeNode>
